reydb/__init__.py
reydb/rall.py
reydb/rbase.py
reydb/rbuild.py
reydb/rconfig.py
reydb/rconn.py
reydb/rdb.py
reydb/rengine.py
reydb/rerror.py
reydb/rexec.py
reydb/rinfo.py
reydb/rorm.py
reydb-1.3.33.dist-info/METADATA
reydb-1.3.33.dist-info/WHEEL
reydb-1.3.33.dist-info/licenses/LICENSE
reydb-1.3.33.dist-info/RECORD
