Metadata-Version: 2.4
Name: reydb
Version: 1.3.33
Summary: Database method set.
Project-URL: homepage, https://github.com/reyxbo/reydb/
Author-email: Rey <reyxbo@163.com>
License: Copyright 2025 ReyXBo
License-File: LICENSE
Keywords: PostgreSQL,async,asynchronous,database,db,orm,postgres,rey,reyxbo
Requires-Python: >=3.12
Requires-Dist: asyncpg
Requires-Dist: psycopg[binary]
Requires-Dist: pydantic[email]
Requires-Dist: reykit
Requires-Dist: sqlalchemy==2.0.42
Requires-Dist: sqlmodel
